incenp/__init__.py
incenp/bio/__init__.py
incenp/bio/seqio/GckIO.py
incenp/bio/seqio/SnapGeneIO.py
incenp/bio/seqio/XdnaIO.py
incenp/bio/seqio/__init__.py
incenp.binseqs-0.2.1.dist-info/AUTHORS
incenp.binseqs-0.2.1.dist-info/LICENSE.txt
incenp.binseqs-0.2.1.dist-info/METADATA
incenp.binseqs-0.2.1.dist-info/WHEEL
incenp.binseqs-0.2.1.dist-info/top_level.txt
incenp.binseqs-0.2.1.dist-info/RECORD
