Metadata-Version: 2.1
Name: incenp.binseqs
Version: 0.2.1
Summary: Support for binary sequence formats in Biopython
Home-page: https://git.incenp.org/damien/binseqs
Author: Damien Goutte-Gattat
Author-email: dgouttegattat@incenp.org
License: UNKNOWN
Platform: UNKNOWN
Classifier: Development Status :: 1 - Planning
Classifier: Environment :: Console
Classifier: Intended Audience :: Science/Research
Classifier: License :: OSI Approved :: BSD License
Classifier: Programming Language :: Python :: 2.7
Classifier: Programming Language :: Python :: 3.6
Classifier: Programming Language :: Python :: 3.7
Classifier: Topic :: Scientific/Engineering :: Bio-Informatics
Requires-Dist: biopython
